<?xml version="1.0" encoding="UTF-8"?>
<!DOCTYPE mapper PUBLIC "-//mybatis.org//DTD Mapper 3.0//EN" "http://mybatis.org/dtd/mybatis-3-mapper.dtd">
<mapper namespace="com.piesat.dao.mapper.TSodDeptMapper">
  <resultMap id="BaseResultMap" type="com.piesat.model.mybatis.TSodDept">
    <!--
      WARNING - @mbg.generated
      This element is automatically generated by MyBatis Generator, do not modify.
    -->
    <id column="ID" jdbcType="VARCHAR" property="id" />
    <result column="CREATE_BY" jdbcType="VARCHAR" property="createBy" />
    <result column="CREATE_TIME" jdbcType="TIMESTAMP" property="createTime" />
    <result column="DEL_FLAG" jdbcType="VARCHAR" property="delFlag" />
    <result column="UPDATE_BY" jdbcType="VARCHAR" property="updateBy" />
    <result column="UPDATE_TIME" jdbcType="TIMESTAMP" property="updateTime" />
    <result column="VERSION" jdbcType="INTEGER" property="version" />
    <result column="ANCESTORS" jdbcType="VARCHAR" property="ancestors" />
    <result column="DEPT_NAME" jdbcType="VARCHAR" property="deptName" />
    <result column="EMAIL" jdbcType="VARCHAR" property="email" />
    <result column="LEADER" jdbcType="VARCHAR" property="leader" />
    <result column="ORDER_NUM" jdbcType="INTEGER" property="orderNum" />
    <result column="PARENT_ID" jdbcType="VARCHAR" property="parentId" />
    <result column="PHONE" jdbcType="VARCHAR" property="phone" />
    <result column="STATUS" jdbcType="VARCHAR" property="status" />
  </resultMap>
  <sql id="Base_Column_List">
    <!--
      WARNING - @mbg.generated
      This element is automatically generated by MyBatis Generator, do not modify.
    -->
    ID, CREATE_BY, CREATE_TIME, DEL_FLAG, UPDATE_BY, UPDATE_TIME, VERSION, ANCESTORS, 
    DEPT_NAME, EMAIL, LEADER, ORDER_NUM, PARENT_ID, PHONE, STATUS
  </sql>
  <select id="selectByPrimaryKey" parameterType="java.lang.String" resultMap="BaseResultMap">
    <!--
      WARNING - @mbg.generated
      This element is automatically generated by MyBatis Generator, do not modify.
    -->
    select 
    <include refid="Base_Column_List" />
    from T_SOD_DEPT
    where ID = #{id,jdbcType=VARCHAR}
  </select>
  <delete id="deleteByPrimaryKey" parameterType="java.lang.String">
    <!--
      WARNING - @mbg.generated
      This element is automatically generated by MyBatis Generator, do not modify.
    -->
    delete from T_SOD_DEPT
    where ID = #{id,jdbcType=VARCHAR}
  </delete>
  <insert id="insert" parameterType="com.piesat.model.mybatis.TSodDept">
    <!--
      WARNING - @mbg.generated
      This element is automatically generated by MyBatis Generator, do not modify.
    -->
    insert into T_SOD_DEPT (ID, CREATE_BY, CREATE_TIME, 
      DEL_FLAG, UPDATE_BY, UPDATE_TIME, 
      VERSION, ANCESTORS, DEPT_NAME, 
      EMAIL, LEADER, ORDER_NUM, 
      PARENT_ID, PHONE, STATUS
      )
    values (#{id,jdbcType=VARCHAR}, #{createBy,jdbcType=VARCHAR}, #{createTime,jdbcType=TIMESTAMP}, 
      #{delFlag,jdbcType=VARCHAR}, #{updateBy,jdbcType=VARCHAR}, #{updateTime,jdbcType=TIMESTAMP}, 
      #{version,jdbcType=INTEGER}, #{ancestors,jdbcType=VARCHAR}, #{deptName,jdbcType=VARCHAR}, 
      #{email,jdbcType=VARCHAR}, #{leader,jdbcType=VARCHAR}, #{orderNum,jdbcType=INTEGER}, 
      #{parentId,jdbcType=VARCHAR}, #{phone,jdbcType=VARCHAR}, #{status,jdbcType=VARCHAR}
      )
  </insert>
  <insert id="insertSelective" parameterType="com.piesat.model.mybatis.TSodDept">
    <!--
      WARNING - @mbg.generated
      This element is automatically generated by MyBatis Generator, do not modify.
    -->
    insert into T_SOD_DEPT
    <trim prefix="(" suffix=")" suffixOverrides=",">
      <if test="id != null">
        ID,
      </if>
      <if test="createBy != null">
        CREATE_BY,
      </if>
      <if test="createTime != null">
        CREATE_TIME,
      </if>
      <if test="delFlag != null">
        DEL_FLAG,
      </if>
      <if test="updateBy != null">
        UPDATE_BY,
      </if>
      <if test="updateTime != null">
        UPDATE_TIME,
      </if>
      <if test="version != null">
        VERSION,
      </if>
      <if test="ancestors != null">
        ANCESTORS,
      </if>
      <if test="deptName != null">
        DEPT_NAME,
      </if>
      <if test="email != null">
        EMAIL,
      </if>
      <if test="leader != null">
        LEADER,
      </if>
      <if test="orderNum != null">
        ORDER_NUM,
      </if>
      <if test="parentId != null">
        PARENT_ID,
      </if>
      <if test="phone != null">
        PHONE,
      </if>
      <if test="status != null">
        STATUS,
      </if>
    </trim>
    <trim prefix="values (" suffix=")" suffixOverrides=",">
      <if test="id != null">
        #{id,jdbcType=VARCHAR},
      </if>
      <if test="createBy != null">
        #{createBy,jdbcType=VARCHAR},
      </if>
      <if test="createTime != null">
        #{createTime,jdbcType=TIMESTAMP},
      </if>
      <if test="delFlag != null">
        #{delFlag,jdbcType=VARCHAR},
      </if>
      <if test="updateBy != null">
        #{updateBy,jdbcType=VARCHAR},
      </if>
      <if test="updateTime != null">
        #{updateTime,jdbcType=TIMESTAMP},
      </if>
      <if test="version != null">
        #{version,jdbcType=INTEGER},
      </if>
      <if test="ancestors != null">
        #{ancestors,jdbcType=VARCHAR},
      </if>
      <if test="deptName != null">
        #{deptName,jdbcType=VARCHAR},
      </if>
      <if test="email != null">
        #{email,jdbcType=VARCHAR},
      </if>
      <if test="leader != null">
        #{leader,jdbcType=VARCHAR},
      </if>
      <if test="orderNum != null">
        #{orderNum,jdbcType=INTEGER},
      </if>
      <if test="parentId != null">
        #{parentId,jdbcType=VARCHAR},
      </if>
      <if test="phone != null">
        #{phone,jdbcType=VARCHAR},
      </if>
      <if test="status != null">
        #{status,jdbcType=VARCHAR},
      </if>
    </trim>
  </insert>
  <update id="updateByPrimaryKeySelective" parameterType="com.piesat.model.mybatis.TSodDept">
    <!--
      WARNING - @mbg.generated
      This element is automatically generated by MyBatis Generator, do not modify.
    -->
    update T_SOD_DEPT
    <set>
      <if test="createBy != null">
        CREATE_BY = #{createBy,jdbcType=VARCHAR},
      </if>
      <if test="createTime != null">
        CREATE_TIME = #{createTime,jdbcType=TIMESTAMP},
      </if>
      <if test="delFlag != null">
        DEL_FLAG = #{delFlag,jdbcType=VARCHAR},
      </if>
      <if test="updateBy != null">
        UPDATE_BY = #{updateBy,jdbcType=VARCHAR},
      </if>
      <if test="updateTime != null">
        UPDATE_TIME = #{updateTime,jdbcType=TIMESTAMP},
      </if>
      <if test="version != null">
        VERSION = #{version,jdbcType=INTEGER},
      </if>
      <if test="ancestors != null">
        ANCESTORS = #{ancestors,jdbcType=VARCHAR},
      </if>
      <if test="deptName != null">
        DEPT_NAME = #{deptName,jdbcType=VARCHAR},
      </if>
      <if test="email != null">
        EMAIL = #{email,jdbcType=VARCHAR},
      </if>
      <if test="leader != null">
        LEADER = #{leader,jdbcType=VARCHAR},
      </if>
      <if test="orderNum != null">
        ORDER_NUM = #{orderNum,jdbcType=INTEGER},
      </if>
      <if test="parentId != null">
        PARENT_ID = #{parentId,jdbcType=VARCHAR},
      </if>
      <if test="phone != null">
        PHONE = #{phone,jdbcType=VARCHAR},
      </if>
      <if test="status != null">
        STATUS = #{status,jdbcType=VARCHAR},
      </if>
    </set>
    where ID = #{id,jdbcType=VARCHAR}
  </update>
  <update id="updateByPrimaryKey" parameterType="com.piesat.model.mybatis.TSodDept">
    <!--
      WARNING - @mbg.generated
      This element is automatically generated by MyBatis Generator, do not modify.
    -->
    update T_SOD_DEPT
    set CREATE_BY = #{createBy,jdbcType=VARCHAR},
      CREATE_TIME = #{createTime,jdbcType=TIMESTAMP},
      DEL_FLAG = #{delFlag,jdbcType=VARCHAR},
      UPDATE_BY = #{updateBy,jdbcType=VARCHAR},
      UPDATE_TIME = #{updateTime,jdbcType=TIMESTAMP},
      VERSION = #{version,jdbcType=INTEGER},
      ANCESTORS = #{ancestors,jdbcType=VARCHAR},
      DEPT_NAME = #{deptName,jdbcType=VARCHAR},
      EMAIL = #{email,jdbcType=VARCHAR},
      LEADER = #{leader,jdbcType=VARCHAR},
      ORDER_NUM = #{orderNum,jdbcType=INTEGER},
      PARENT_ID = #{parentId,jdbcType=VARCHAR},
      PHONE = #{phone,jdbcType=VARCHAR},
      STATUS = #{status,jdbcType=VARCHAR}
    where ID = #{id,jdbcType=VARCHAR}
  </update>
</mapper>